{
  "name": "Elmotorstyrning",
  "code": "INSELS0",
  "centralContent": {
    "sections": [
      {
        "title": "Undervisningen i kursen ska behandla följande centrala innehåll:",
        "rows": [
          "1. Installation av elmotorer med tillhörande skyddsanordningar.",
          "2. Installation av styrutrustning för styrning av elmotorer.",
          "3. Installation av varvtalsreglering och mjukstartare.",
          "4. Lagar och andra bestämmelser om säkerhet inom området. Standarder.",
          "5. Val av ledningar med hänsyn till störningar och olika miljöer.",
          "6. Driftsättning och underhåll av elmotorer med tillhörande skyddsanordningar, styrutrustningar och automatikutrustningar.",
          "7. Dokumentation gällande elmotorer, styrutrustningar och automatikutrustningar.",
          "8. Felsökning och felavhjälpning av elmotorer med tillhörande skyddsanordningar, styrutrustningar och automatikutrustningar."
        ]
      }
    ]
  }
}