{
  "name": "Modersmål – aktiv tvåspråkighet",
  "code": "MOEMOD0",
  "centralContent": {
    "sections": [
      {
        "title": "Undervisningen i kursen ska behandla följande centrala innehåll:",
        "rows": [
          "1. Kommunikation i tal och skrift, till exempel med myndigheter, högskolor och arbetsgivare.",
          "2. Informella brev som syftar till social kommunikation.",
          "3. Ord- och begreppsförråd med särskild tonvikt på ord som hör till medborgarrollen och samhällslivet.",
          "4. Tolkning och översättning i vardagliga sammanhang till och från modersmålet.",
          "5. Översättning till modersmålet av olika blanketter som medborgare i Sverige använder.",
          "6. Texter i form av berättelser och dikter inom modern litteratur på modersmålet och texter från svensk litteratur för olika typer av jämförelser.",
          "7. Aktuella samhällsfrågor. Jämförande studier mellan länder där modersmålet talas och Sverige.",
          "8. Kulturella företeelser och sevärdheter. Jämförande studier mellan länder där modersmålet talas och Sverige."
        ]
      }
    ]
  }
}