{
  "name": "Styckning – specialisering",
  "code": "STCSTY00S",
  "centralContent": {
    "sections": [
      {
        "title": "Undervisningen i kursen ska behandla följande centrala innehåll:",
        "rows": [
          "1. Djurens anatomi inom valt specialiseringsområde, till exempel vilt eller struts.",
          "2. Styckningsdetaljernas och de olika sorteringarnas användningsområden vid förädling och tillagning inom valt specialiseringsområde.",
          "3. Branschkrav då det gäller kvalitet och produktionens effektivitet.",
          "4. Trender, influenser och utveckling inom valt specialiseringsområde.",
          "5. Yrkesmässig styckning inom valt specialiseringsområde. Exempel på specialiseringsområde kan vara styckning av vilt eller struts.",
          "6. Lönsamhet och ekonomiska konsekvenser vid val av inköp av kött samt sambandet mellan styckningskvalitet och ekonomi.",
          "7. Metoder och teknik.",
          "8. Användning och vård av utrustning.",
          "9. Planering och organisation av arbetet.",
          "10. Lagar och andra bestämmelser inom yrkesområdet.",
          "11. Arbetsmiljö och säkerhet.",
          "12. Hygien och egenkontroll."
        ]
      }
    ]
  }
}